{
  "updated_at": null,
  "platforms": {
    "telegram": [
      {
        "id": "{{ADMIN_TELEGRAM_ID}}",
        "name": "{{ADMIN_NAME}}",
        "type": "dm",
        "thread_id": null
      },
      {
        "id": "{{OWNER_TELEGRAM_ID}}",
        "name": "{{OWNER_NAME}}",
        "type": "dm",
        "thread_id": null
      }
    ],
    "discord": [],
    "whatsapp": [
      {
        "id": "{{WHATSAPP_PHONE_NUMBER}}",
        "name": "{{OWNER_NAME}}",
        "type": "dm",
        "thread_id": null
      }
    ],
    "slack": [],
    "signal": [],
    "sms": [],
    "email": []
  }
}
